wordnet_mcp_server/__init__.py
wordnet_mcp_server/__main__.py
wordnet_mcp_server/app.py
wordnet_mcp_server-0.1.10.dist-info/METADATA
wordnet_mcp_server-0.1.10.dist-info/WHEEL
wordnet_mcp_server-0.1.10.dist-info/entry_points.txt
wordnet_mcp_server-0.1.10.dist-info/top_level.txt
wordnet_mcp_server-0.1.10.dist-info/RECORD
