Metadata-Version: 2.4
Name: wordnet-mcp-server
Version: 0.1.10
Summary: WordNet词汇查询的MCP服务
Author: keepondream
License: MIT
Project-URL: Homepage, https://github.com/keepondream/wordnet-mcp-server
Project-URL: Bug Tracker, https://github.com/keepondream/wordnet-mcp-server/issues
Project-URL: Source Code, https://github.com/keepondream/wordnet-mcp-server
Requires-Python: >=3.9
Requires-Dist: mcp[cli]
Requires-Dist: nltk
Provides-Extra: dev
Requires-Dist: ruff; extra == "dev"
Requires-Dist: pytest; extra == "dev"
